cyrebro_domain_validator/__init__.py
cyrebro_domain_validator/domain_validator.py
cyrebro_domain_validator-0.3.2.dist-info/LICENSE
cyrebro_domain_validator-0.3.2.dist-info/METADATA
cyrebro_domain_validator-0.3.2.dist-info/WHEEL
cyrebro_domain_validator-0.3.2.dist-info/top_level.txt
cyrebro_domain_validator-0.3.2.dist-info/RECORD
