Metadata-Version: 2.2
Name: cyrebro_domain_validator
Version: 0.3.2
Summary: A domain validation package, written by CYREBRO's Innovation team.
Home-page: https://github.com/CYREBRO/cyrebro-domain-validator
Author: CYREBRO Innovation
Author-email: innovation@cyrebro.io
License: MIT
Classifier: Intended Audience :: Developers
Classifier: License :: OSI Approved :: MIT License
Classifier: Natural Language :: English
Classifier: Programming Language :: Python :: 3
Classifier: Topic :: Software Development :: Libraries :: Python Modules
Classifier: Operating System :: OS Independent
License-File: LICENSE
Requires-Dist: requests
Requires-Dist: dnspython>=2.2.1
Requires-Dist: tld>=0.12.6
Requires-Dist: tenacity
Dynamic: author
Dynamic: author-email
Dynamic: classifier
Dynamic: description
Dynamic: description-content-type
Dynamic: home-page
Dynamic: license
Dynamic: requires-dist
Dynamic: summary
